gtfo/__init__.py
gtfo/cli.py
gtfo/data/apt-get.json
gtfo/data/apt.json
gtfo/data/ar.json
gtfo/data/aria2c.json
gtfo/data/arp.json
gtfo/data/ash.json
gtfo/data/at.json
gtfo/data/atobm.json
gtfo/data/awk.json
gtfo/data/base32.json
gtfo/data/base64.json
gtfo/data/basenc.json
gtfo/data/bash.json
gtfo/data/bpftrace.json
gtfo/data/bundler.json
gtfo/data/busctl.json
gtfo/data/busybox.json
gtfo/data/byebug.json
gtfo/data/cancel.json
gtfo/data/capsh.json
gtfo/data/cat.json
gtfo/data/certbot.json
gtfo/data/check_by_ssh.json
gtfo/data/check_cups.json
gtfo/data/check_log.json
gtfo/data/check_memory.json
gtfo/data/check_raid.json
gtfo/data/check_ssl_cert.json
gtfo/data/check_statusfile.json
gtfo/data/chmod.json
gtfo/data/chown.json
gtfo/data/chroot.json
gtfo/data/cobc.json
gtfo/data/column.json
gtfo/data/comm.json
gtfo/data/composer.json
gtfo/data/cowsay.json
gtfo/data/cowthink.json
gtfo/data/cp.json
gtfo/data/cpan.json
gtfo/data/cpio.json
gtfo/data/cpulimit.json
gtfo/data/crash.json
gtfo/data/crontab.json
gtfo/data/csh.json
gtfo/data/csplit.json
gtfo/data/csvtool.json
gtfo/data/cupsfilter.json
gtfo/data/curl.json
gtfo/data/cut.json
gtfo/data/dash.json
gtfo/data/date.json
gtfo/data/dd.json
gtfo/data/dialog.json
gtfo/data/diff.json
gtfo/data/dig.json
gtfo/data/dmesg.json
gtfo/data/dmsetup.json
gtfo/data/dnf.json
gtfo/data/docker.json
gtfo/data/dpkg.json
gtfo/data/dvips.json
gtfo/data/easy_install.json
gtfo/data/eb.json
gtfo/data/ed.json
gtfo/data/emacs.json
gtfo/data/env.json
gtfo/data/eqn.json
gtfo/data/ex.json
gtfo/data/exiftool.json
gtfo/data/expand.json
gtfo/data/expect.json
gtfo/data/facter.json
gtfo/data/file.json
gtfo/data/find.json
gtfo/data/finger.json
gtfo/data/flock.json
gtfo/data/fmt.json
gtfo/data/fold.json
gtfo/data/ftp.json
gtfo/data/gawk.json
gtfo/data/gcc.json
gtfo/data/gdb.json
gtfo/data/gem.json
gtfo/data/genisoimage.json
gtfo/data/ghc.json
gtfo/data/ghci.json
gtfo/data/gimp.json
gtfo/data/git.json
gtfo/data/grep.json
gtfo/data/gtester.json
gtfo/data/gzip.json
gtfobins_cli-1.0.0.dist-info/licenses/LICENSE
gtfobins_cli-1.0.0.dist-info/METADATA
gtfobins_cli-1.0.0.dist-info/WHEEL
gtfobins_cli-1.0.0.dist-info/entry_points.txt
gtfobins_cli-1.0.0.dist-info/top_level.txt
gtfobins_cli-1.0.0.dist-info/RECORD
