Metadata-Version: 2.4
Name: gtfobins-cli
Version: 1.0.0
Summary: Command-line tool for GTFOBins - Unix binaries exploitation helper
Home-page: https://github.com/t0thkr1s/gtfo
Author: t0thkr1s
Author-email: t0thkr1s <t0thkr1s@icloud.com>
License: GPL-3.0
Project-URL: Homepage, https://github.com/t0thkr1s/gtfo
Project-URL: Repository, https://github.com/t0thkr1s/gtfo
Project-URL: Issues, https://github.com/t0thkr1s/gtfo/issues
Keywords: gtfobins,security,exploitation,privilege-escalation,pentesting
Classifier: Development Status :: 5 - Production/Stable
Classifier: Environment :: Console
Classifier: Intended Audience :: Developers
Classifier: Intended Audience :: System Administrators
Classifier: Intended Audience :: Information Technology
Classifier: License :: OSI Approved :: GNU General Public License v3 (GPLv3)
Classifier: Operating System :: OS Independent
Classifier: Programming Language :: Python :: 3
Classifier: Programming Language :: Python :: 3.6
Classifier: Programming Language :: Python :: 3.7
Classifier: Programming Language :: Python :: 3.8
Classifier: Programming Language :: Python :: 3.9
Classifier: Programming Language :: Python :: 3.10
Classifier: Programming Language :: Python :: 3.11
Classifier: Programming Language :: Python :: 3.12
Classifier: Topic :: Security
Classifier: Topic :: System :: System Shells
Classifier: Topic :: Utilities
Requires-Python: >=3.6
License-File: LICENSE
Requires-Dist: colorama>=0.4.0
Requires-Dist: pygments>=2.0.0
Dynamic: author
Dynamic: home-page
Dynamic: license-file
Dynamic: requires-python
